zcatalyst_sdk/__init__.py
zcatalyst_sdk/__version__.py
zcatalyst_sdk/_constants.py
zcatalyst_sdk/_http_client.py
zcatalyst_sdk/_thread_util.py
zcatalyst_sdk/_util.py
zcatalyst_sdk/authentication.py
zcatalyst_sdk/catalyst_app.py
zcatalyst_sdk/circuit.py
zcatalyst_sdk/credentials.py
zcatalyst_sdk/cron.py
zcatalyst_sdk/email.py
zcatalyst_sdk/exceptions.py
zcatalyst_sdk/functions.py
zcatalyst_sdk/logger.py
zcatalyst_sdk/pipeline.py
zcatalyst_sdk/quick_ml.py
zcatalyst_sdk/search.py
zcatalyst_sdk/smart_browz.py
zcatalyst_sdk/validator.py
zcatalyst_sdk/zcql.py
zcatalyst_sdk/zia.py
zcatalyst_sdk/cache/__init__.py
zcatalyst_sdk/cache/_segment.py
zcatalyst_sdk/connection/__init__.py
zcatalyst_sdk/connection/_connector.py
zcatalyst_sdk/datastore/__init__.py
zcatalyst_sdk/datastore/_bulk_job.py
zcatalyst_sdk/datastore/_table.py
zcatalyst_sdk/filestore/__init__.py
zcatalyst_sdk/filestore/_folder.py
zcatalyst_sdk/job_scheduling/__init__.py
zcatalyst_sdk/job_scheduling/_cron.py
zcatalyst_sdk/job_scheduling/_exception.py
zcatalyst_sdk/job_scheduling/_job.py
zcatalyst_sdk/job_scheduling/_types.py
zcatalyst_sdk/nosql/__init__.py
zcatalyst_sdk/nosql/_table_items.py
zcatalyst_sdk/nosql/conditions.py
zcatalyst_sdk/nosql/transfom.py
zcatalyst_sdk/nosql/types.py
zcatalyst_sdk/push_notification/__init__.py
zcatalyst_sdk/push_notification/_mobile_notification.py
zcatalyst_sdk/push_notification/_web_notificaton.py
zcatalyst_sdk/stratus/__init__.py
zcatalyst_sdk/stratus/_auth_util.py
zcatalyst_sdk/stratus/bucket.py
zcatalyst_sdk/stratus/object.py
zcatalyst_sdk/stratus/transfer_manager.py
zcatalyst_sdk/types/__init__.py
zcatalyst_sdk/types/nosql.py
zcatalyst_sdk/types/pipeline.py
zcatalyst_sdk/types/smart_browz.py
zcatalyst_sdk/types/stratus.py
zcatalyst_sdk/types/zia.py
zcatalyst_sdk-1.0.2.dist-info/LICENSE
zcatalyst_sdk-1.0.2.dist-info/METADATA
zcatalyst_sdk-1.0.2.dist-info/WHEEL
zcatalyst_sdk-1.0.2.dist-info/top_level.txt
zcatalyst_sdk-1.0.2.dist-info/RECORD
