Metadata-Version: 2.1
Name: zcatalyst_sdk
Version: 1.0.2
Summary: Zoho Catalyst SDK for Python
Home-page: https://catalyst.zoho.com/
Author: Catalyst by Zoho
Author-email: support@zohocatalyst.com
License: Apache License 2.0
Keywords: zcatalyst,zoho,catalyst,serverless,cloud,SDK,development
Classifier: Programming Language :: Python :: 3
Classifier: Programming Language :: Python :: 3.9
Classifier: License :: OSI Approved :: Apache Software License
Classifier: Operating System :: OS Independent
Classifier: Development Status :: 4 - Beta
Classifier: Intended Audience :: Developers
Requires-Python: >= 3.9
License-File: LICENSE
Requires-Dist: requests~=2.32.3
Requires-Dist: typing-extensions~=4.12.1
